stuser/BQTools.py
stuser/Email.py
stuser/ErrorHandling.py
stuser/Forms.py
stuser/Hasher.py
stuser/Validator.py
stuser/Verification.py
stuser/__init__.py
stuser-0.0.3.dist-info/LICENSE
stuser-0.0.3.dist-info/METADATA
stuser-0.0.3.dist-info/WHEEL
stuser-0.0.3.dist-info/top_level.txt
stuser-0.0.3.dist-info/RECORD
